pyramid_celery/__init__.py
pyramid_celery/loaders.py
pyramid_celery-4.0.0.dist-info/LICENSE
pyramid_celery-4.0.0.dist-info/METADATA
pyramid_celery-4.0.0.dist-info/WHEEL
pyramid_celery-4.0.0.dist-info/top_level.txt
pyramid_celery-4.0.0.dist-info/RECORD
