Metadata-Version: 2.1
Name: pyramid-celery
Version: 4.0.0
Summary: Celery integration with pyramid
Home-page: https://github.com/sontek/pyramid_celery
Author: John Anderson
Author-email: sontek@gmail.com
License: MIT
Keywords: paste pyramid celery message queue amqp job task distributed
Platform: UNKNOWN
Classifier: Development Status :: 5 - Production/Stable
Classifier: Intended Audience :: Developers
Classifier: License :: OSI Approved :: MIT License
Classifier: Operating System :: Unix
Classifier: Operating System :: POSIX
Classifier: Operating System :: Microsoft :: Windows
Classifier: Programming Language :: Python
Classifier: Programming Language :: Python :: 3
Classifier: Programming Language :: Python :: 3.6
Classifier: Programming Language :: Python :: 3.7
Classifier: Programming Language :: Python :: 3.8
Classifier: Programming Language :: Python :: 3.9
Classifier: Programming Language :: Python :: Implementation :: CPython
Classifier: Programming Language :: Python :: Implementation :: PyPy
Requires-Python: >=3.6
Requires-Dist: pyramid
Requires-Dist: celery
